python_q4m
