Metadata-Version: 1.0
Name: python_q4m
Version: 0.0.6
Summary: Q4M operation wrapper
Home-page: http://github.com/cubicdaiya/python-q4m
Author: Tatsuhiko Kubo (cubicdaiya@gmail.com)
Author-email: cubicdaiya@gmail.com
License: GPL2
Keywords: q4m,mysql,queue
Platform: UNKNOWN
Classifier: Development Status :: 5 - Production/Stable
Classifier: Intended Audience :: Developers
Classifier: License :: OSI Approved :: GNU General Public License (GPL)
Classifier: Programming Language :: Python
Classifier: Topic :: Software Development :: Libraries :: Python Modules
